turborequests.py
turborequests-1.0.0.dist-info/LICENSE
turborequests-1.0.0.dist-info/WHEEL
turborequests-1.0.0.dist-info/METADATA
turborequests-1.0.0.dist-info/RECORD
